weditor_assistant/__init__.py
weditor_assistant/test.py
weditor_assistant/weditor_assistant.py
weditor_assistant-0.2.3.dist-info/METADATA
weditor_assistant-0.2.3.dist-info/WHEEL
weditor_assistant-0.2.3.dist-info/top_level.txt
weditor_assistant-0.2.3.dist-info/RECORD
