Metadata-Version: 2.1
Name: weditor-assistant
Version: 0.2.3
Summary: string to date
Home-page: UNKNOWN
Author: zxw
Author-email: 761479698@qq.com
License: MIT
Platform: UNKNOWN
